chaosgrafana/__init__.py
chaosgrafana/controls/__init__.py
chaosgrafana/controls/loki.py
chaostoolkit_grafana-0.2.0.dist-info/LICENSE
chaostoolkit_grafana-0.2.0.dist-info/METADATA
chaostoolkit_grafana-0.2.0.dist-info/WHEEL
chaostoolkit_grafana-0.2.0.dist-info/top_level.txt
chaostoolkit_grafana-0.2.0.dist-info/RECORD
