Metadata-Version: 2.1
Name: chaostoolkit-grafana
Version: 0.2.0
Summary: Chaos Toolkit extension sending logs/metrics to Grafana
Home-page: https://chaostoolkit.org
Author: Chaos Toolkit
Author-email: contact@chaostoolkit.org
License: Apache License Version 2.0
Project-URL: Docs: RTD, https://chaostoolkit.org
Project-URL: CI: GitHub, https://github.com/chaostoolkit-incubator/chaostoolkit-grafana/actions
Project-URL: GitHub: issues, https://github.com/chaostoolkit-incubator/chaostoolkit-grafana/issues
Project-URL: GitHub: repo, https://github.com/chaostoolkit-incubator/chaostoolkit-grafana
Platform: any
Classifier: Development Status :: 5 - Production/Stable
Classifier: Intended Audience :: Developers
Classifier: License :: Freely Distributable
Classifier: License :: OSI Approved :: Apache Software License
Classifier: Operating System :: OS Independent
Classifier: Programming Language :: Python
Classifier: Programming Language :: Python :: 3
Classifier: Programming Language :: Python :: 3.7
Classifier: Programming Language :: Python :: 3.8
Classifier: Programming Language :: Python :: 3.9
Classifier: Programming Language :: Python :: 3.10
Classifier: Programming Language :: Python :: Implementation
Classifier: Programming Language :: Python :: Implementation :: CPython
Requires-Python: >=3.7
License-File: LICENSE
Requires-Dist: chaostoolkit-lib (~=1.27)
Requires-Dist: python-logging-loki (~=0.3)
